fastapi_fs_router/__init__.py
fastapi_fs_router/load_fs_router.py
fastapi_fs_router/py.typed
fastapi_fs_router-0.1.1.dist-info/METADATA
fastapi_fs_router-0.1.1.dist-info/WHEEL
fastapi_fs_router-0.1.1.dist-info/licenses/LICENSE
fastapi_fs_router-0.1.1.dist-info/RECORD
