Metadata-Version: 2.4
Name: fastapi-fs-router
Version: 0.1.1
Summary: Add your description here
Author-email: owjs3901 <owjs3901@gmail.com>
License-File: LICENSE
Requires-Python: >=3.9
